Metadata-Version: 1.0
Name: imagediffer
Version: 0.1.4
Summary: Tool for image diffs.
Home-page: https://github.com/janslifka/imagediffer
Author: Jan Slifka
Author-email: slifkjan@fit.cvut.cz
License: UNKNOWN
Platform: UNKNOWN
